{
  "/[slug]/page": "app/[slug]/page.js",
  "/_global-error/page": "app/_global-error/page.js",
  "/_not-found/page": "app/_not-found/page.js",
  "/api/check-slug/route": "app/api/check-slug/route.js",
  "/api/register/route": "app/api/register/route.js",
  "/api/upload/route": "app/api/upload/route.js",
  "/api/verify/route": "app/api/verify/route.js",
  "/apple-icon.png/route": "app/apple-icon.png/route.js",
  "/favicon.ico/route": "app/favicon.ico/route.js",
  "/icon.png/route": "app/icon.png/route.js",
  "/page": "app/page.js",
  "/qr/page": "app/qr/page.js",
  "/register/page": "app/register/page.js"
}